mlflow/__init__.py
mlflow/cli.py
mlflow/data.py
mlflow/db.py
mlflow/exceptions.py
mlflow/experiments.py
mlflow/pydantic_v1.py
mlflow/runs.py
mlflow/version.py
mlflow/config/__init__.py
mlflow/config/config.py
mlflow/config/generate_config.py
mlflow/dto/__init__.py
mlflow/dto/artifacts_dto.py
mlflow/dto/auth_dto.py
mlflow/dto/common_dto.py
mlflow/dto/experiments_dto.py
mlflow/dto/metrics_dto.py
mlflow/dto/mlfoundry_artifacts_dto.py
mlflow/dto/python_deployment_config_dto.py
mlflow/dto/runs_dto.py
mlflow/entities/__init__.py
mlflow/entities/_mlflow_object.py
mlflow/entities/auth_enums.py
mlflow/entities/columns.py
mlflow/entities/experiment.py
mlflow/entities/experiment_tag.py
mlflow/entities/file_info.py
mlflow/entities/lifecycle_stage.py
mlflow/entities/metric.py
mlflow/entities/param.py
mlflow/entities/run.py
mlflow/entities/run_data.py
mlflow/entities/run_info.py
mlflow/entities/run_log.py
mlflow/entities/run_status.py
mlflow/entities/run_tag.py
mlflow/entities/sentinel.py
mlflow/entities/signed_url.py
mlflow/entities/source_type.py
mlflow/entities/storage_integration.py
mlflow/entities/user_info.py
mlflow/entities/view_type.py
mlflow/entities/autogen/__init__.py
mlflow/entities/autogen/prompt.py
mlflow/entities/mlfoundry_artifacts/__init__.py
mlflow/entities/mlfoundry_artifacts/artifact.py
mlflow/entities/mlfoundry_artifacts/artifact_version_in_transit.py
mlflow/entities/mlfoundry_artifacts/custom_metric.py
mlflow/entities/mlfoundry_artifacts/enums.py
mlflow/entities/mlfoundry_artifacts/model.py
mlflow/entities/mlfoundry_artifacts/multipart_upload.py
mlflow/entities/mlfoundry_artifacts/utils.py
mlflow/entities/mlfoundry_artifacts/datasets/__init__.py
mlflow/entities/mlfoundry_artifacts/datasets/dataset.py
mlflow/protos/__init__.py
mlflow/protos/databricks_pb2.py
mlflow/protos/scalapb/__init__.py
mlflow/protos/scalapb/scalapb_pb2.py
mlflow/store/__init__.py
mlflow/store/utils.py
mlflow/store/artifact/__init__.py
mlflow/store/artifact/artifact_repo.py
tfy_mlflow_client-0.0.56.dist-info/LICENSE.txt
tfy_mlflow_client-0.0.56.dist-info/METADATA
tfy_mlflow_client-0.0.56.dist-info/WHEEL
tfy_mlflow_client-0.0.56.dist-info/top_level.txt
tfy_mlflow_client-0.0.56.dist-info/RECORD
