Metadata-Version: 2.1
Name: tfy-mlflow-client
Version: 0.0.56
License-File: LICENSE.txt
Requires-Dist: setuptools
Requires-Dist: click>=7.0
Requires-Dist: entrypoints
Requires-Dist: GitPython>=2.1.0
Requires-Dist: PyYAML>=5.1
Requires-Dist: protobuf<6.0,>=3.12
Requires-Dist: pytz
Requires-Dist: requests>=2.17.3
Requires-Dist: packaging
Requires-Dist: importlib-metadata!=4.7.0,>=3.7.0
Requires-Dist: sqlparse>=0.5.0
Requires-Dist: pydantic<3.0.0,>=1.8.2
Requires-Dist: tabulate>=0.7.7
Requires-Dist: oauthlib>=3.1.0
